mantis_api_client/__init__.py
mantis_api_client/cli_parser/account_parser.py
mantis_api_client/cli_parser/attack_parser.py
mantis_api_client/cli_parser/bas_parser.py
mantis_api_client/cli_parser/basebox_parser.py
mantis_api_client/cli_parser/dataset_parser.py
mantis_api_client/cli_parser/lab_parser.py
mantis_api_client/cli_parser/labs_parser.py
mantis_api_client/cli_parser/log_collector_parser.py
mantis_api_client/cli_parser/redteam_parser.py
mantis_api_client/cli_parser/scenario_parser.py
mantis_api_client/cli_parser/signature_parser.py
mantis_api_client/cli_parser/topology_parser.py
mantis_api_client/cli_parser/user_parser.py
mantis_api_client/config.py
mantis_api_client/dataset_api.py
mantis_api_client/exceptions.py
mantis_api_client/mantis.py
mantis_api_client/oidc.py
mantis_api_client/scenario_api.py
mantis_api_client/user_api.py
mantis_api_client/utils.py
mantis_api_client-5.4.0.dist-info/AUTHORS
mantis_api_client-5.4.0.dist-info/LICENSE
mantis_api_client-5.4.0.dist-info/METADATA
mantis_api_client-5.4.0.dist-info/WHEEL
mantis_api_client-5.4.0.dist-info/entry_points.txt
mantis_api_client-5.4.0.dist-info/RECORD
