Metadata-Version: 2.1
Name: mantis_api_client
Version: 5.4.0
Summary: M&NTIS Platform client API
License: MIT
Author: AMOSSYS
Requires-Python: >=3.10,<4.0
Classifier: License :: OSI Approved :: MIT License
Classifier: Programming Language :: Python :: 3
Classifier: Programming Language :: Python :: 3.10
Classifier: Programming Language :: Python :: 3.11
Classifier: Programming Language :: Python :: 3.12
Classifier: Programming Language :: Python :: 3.13
Requires-Dist: alive-progress (>=3.1.5,<4.0.0)
Requires-Dist: argcomplete (>=1.12.1,<1.13.0)
Requires-Dist: colorama (>=0.4.4,<0.5.0)
Requires-Dist: cr-api-client (>=5.0.22,<6.0.0)
Requires-Dist: mantis-authz (>=0.2.3,<1.0.0)
Requires-Dist: mantis-catalog (>=0.1.2,<0.2.0)
Requires-Dist: mantis-logger (>=0.2.0,<0.3.0)
Requires-Dist: mantis-models (>=3.4.0,<4.0.0)
Requires-Dist: omegaconf (>=2.2.2,<3.0.0)
Requires-Dist: pydantic (>=2.10.3,<3.0.0)
Requires-Dist: requests (>=2.24.0,<3.0.0)
Requires-Dist: rich (>=13.7.1,<14.0.0)
Requires-Dist: rich_argparse (>=1.5.2,<2.0.0)
Requires-Dist: ruamel-yaml (>=0.16.10,<0.17.0)
Requires-Dist: ruamel.yaml (>=0.16.10,<0.17.0)
Requires-Dist: termcolor (>=1.1.0,<1.2.0)
